{
    "Items": [
        {
            "title": "Wifi is not on",
            "description": "Help me to turn on the wifi thanks",
            "classification": "IT Issue",
            "issue_type": "WifiNotOn"
        },
        {
            "title": "Wifi on, but cannot connect to internet",
            "description": "Pls help, cannot connect to internet after getting new laptop. Wifi is already on",
            "classification": "IT Issue",
            "issue_type": "WifiOnNoInternet"
        },
        {
            "title": "Cannot access intranet in office",
            "description": "Cannot access intranet resources",
            "classification": "IT Issue",
            "issue_type": "CannotAccessIntranet"
        },
        {
            "title": "VPN Issue",
            "description": "Pls I need to do work from home",
            "classification": "IT Issue",
            "issue_type": "VpnCannotConnect"
        },
        {
            "title": "Computer is slow",
            "description": "Laggy and slow computer",
            "classification": "IT Issue",
            "issue_type": "ComputerSlow"
        }
    ]
}